nba_dataloader/DataFetcher.py
nba_dataloader/__init__.py
nba_dataloader/__main__.py
nba_dataloader-1.0.5.dist-info/LICENSE
nba_dataloader-1.0.5.dist-info/METADATA
nba_dataloader-1.0.5.dist-info/WHEEL
nba_dataloader-1.0.5.dist-info/top_level.txt
nba_dataloader-1.0.5.dist-info/RECORD
