Metadata-Version: 2.1
Name: nba-dataloader
Version: 1.0.5
Summary: A python client to query the various stats.nba.com resources
Author-email: Viddu Devigere <vdevigere@gmail.com>
Project-URL: Homepage, https://github.com/vdevigere/nba_dataloader
Project-URL: Bug Tracker, https://github.com/vdevigere/nba_dataloader/issues
Project-URL: Release Notes, https://github.com/vdevigere/nba_dataloader/releases
Project-URL: PyPi, https://pypi.org/project/nba-dataloader/
Classifier: Programming Language :: Python :: 3
Classifier: License :: OSI Approved :: GNU General Public License (GPL)
Classifier: Operating System :: OS Independent
Requires-Python: >=3.7
License-File: LICENSE
Requires-Dist: requests ==2.31.0
Requires-Dist: pandas ==2.1.2
Requires-Dist: ray ==2.8.0
Requires-Dist: deltalake ==0.13.0
